hope_memory/__init__.py
hope_memory/cache.py
hope_memory/cognitive.py
hope_memory/pool.py
hope_memory/mcp/__init__.py
hope_memory/shp/__init__.py
hope_memory/shp/protocol.py
hope_memory-0.1.1.dist-info/METADATA
hope_memory-0.1.1.dist-info/WHEEL
hope_memory-0.1.1.dist-info/licenses/LICENSE
hope_memory-0.1.1.dist-info/RECORD
