Metadata-Version: 2.4
Name: hope-memory
Version: 0.1.1
Summary: Human-like cognitive memory system for AI with 6-layer architecture and Silent Hope Protocol
Project-URL: Homepage, https://github.com/anthropics/hope-memory
Project-URL: Documentation, https://github.com/anthropics/hope-memory#readme
Project-URL: Repository, https://github.com/anthropics/hope-memory.git
Author-email: Hope + Máté Róbert + Steiner Szilvia <stratosoi@gmail.com>
License-Expression: MIT
License-File: LICENSE
Keywords: ai,chromadb,cognitive,embeddings,llm,memory,protocol,vector-search
Classifier: Development Status :: 4 - Beta
Classifier: Intended Audience :: Developers
Classifier: License :: OSI Approved :: MIT License
Classifier: Programming Language :: Python :: 3
Classifier: Programming Language :: Python :: 3.10
Classifier: Programming Language :: Python :: 3.11
Classifier: Programming Language :: Python :: 3.12
Classifier: Topic :: Scientific/Engineering :: Artificial Intelligence
Requires-Python: >=3.10
Provides-Extra: dev
Requires-Dist: pytest; extra == 'dev'
Requires-Dist: pytest-asyncio; extra == 'dev'
Provides-Extra: full
Requires-Dist: chromadb>=0.4.0; extra == 'full'
Requires-Dist: msgpack>=1.0.0; extra == 'full'
Provides-Extra: shp
Requires-Dist: msgpack>=1.0.0; extra == 'shp'
Provides-Extra: vector
Requires-Dist: chromadb>=0.4.0; extra == 'vector'
